LICENSE
README.md
setup.py
FrameworkDrawer/FrameworkDrawer.py
FrameworkDrawer/FrameworkNode.py
FrameworkDrawer/Signals.py
FrameworkDrawer/__init__.py
FrameworkDrawer.egg-info/PKG-INFO
FrameworkDrawer.egg-info/SOURCES.txt
FrameworkDrawer.egg-info/dependency_links.txt
FrameworkDrawer.egg-info/requires.txt
FrameworkDrawer.egg-info/top_level.txt
FrameworkDrawer/Tests/MyNode.py
FrameworkDrawer/Tests/__init__.py
FrameworkDrawer/Tests/node_test.py